ensure_vpn/__init__.py
ensure_vpn/checkers.py
ensure_vpn/constants.py
ensure_vpn/ensure_vpn.py
ensure_vpn/exceptions.py
ensure_vpn/helpers.py
ensure_vpn/providers.py
ensure_vpn-0.5.0.dist-info/LICENSE
ensure_vpn-0.5.0.dist-info/WHEEL
ensure_vpn-0.5.0.dist-info/METADATA
ensure_vpn-0.5.0.dist-info/RECORD
