Metadata-Version: 2.1
Name: ensure-vpn
Version: 0.5.0
Summary: A function to make sure you are connected to your favorite VPN before running your script.
Home-page: https://github.com/ftruzzi/ensure_vpn
Author: Francesco Truzzi
Author-email: francesco@truzzi.me
Requires-Python: >=3.7,<4.0
Classifier: Programming Language :: Python :: 3
Classifier: Programming Language :: Python :: 3.7
Classifier: Programming Language :: Python :: 3.8
Classifier: Programming Language :: Python :: 3.9
Requires-Dist: beautifulsoup4 (>=4.9.3,<5.0.0)
Requires-Dist: requests (>=2.25.1,<3.0.0)
Project-URL: Repository, https://github.com/ftruzzi/ensure_vpn
